nocv2easyocr/__init__.py
nocv2easyocr/cli.py
nocv2easyocr/config.py
nocv2easyocr/craft.py
nocv2easyocr/craft_utils.py
nocv2easyocr/detection.py
nocv2easyocr/detection_db.py
nocv2easyocr/easyocr.py
nocv2easyocr/export.py
nocv2easyocr/imgproc.py
nocv2easyocr/recognition.py
nocv2easyocr/utils.py
nocv2easyocr/DBNet/DBNet.py
nocv2easyocr/DBNet/README.md
nocv2easyocr/DBNet/assets/ops/dcn/__init__.py
nocv2easyocr/DBNet/assets/ops/dcn/setup.py
nocv2easyocr/DBNet/assets/ops/dcn/functions/__init__.py
nocv2easyocr/DBNet/assets/ops/dcn/functions/deform_conv.py
nocv2easyocr/DBNet/assets/ops/dcn/functions/deform_pool.py
nocv2easyocr/DBNet/assets/ops/dcn/modules/__init__.py
nocv2easyocr/DBNet/assets/ops/dcn/modules/deform_conv.py
nocv2easyocr/DBNet/assets/ops/dcn/modules/deform_pool.py
nocv2easyocr/DBNet/assets/ops/dcn/src/deform_conv_cpu.cpp
nocv2easyocr/DBNet/assets/ops/dcn/src/deform_conv_cpu_kernel.cpp
nocv2easyocr/DBNet/assets/ops/dcn/src/deform_conv_cpu_kernel.h
nocv2easyocr/DBNet/assets/ops/dcn/src/deform_conv_cuda.cpp
nocv2easyocr/DBNet/assets/ops/dcn/src/deform_conv_cuda_kernel.cu
nocv2easyocr/DBNet/assets/ops/dcn/src/deform_pool_cpu.cpp
nocv2easyocr/DBNet/assets/ops/dcn/src/deform_pool_cpu_kernel.cpp
nocv2easyocr/DBNet/assets/ops/dcn/src/deform_pool_cpu_kernel.h
nocv2easyocr/DBNet/assets/ops/dcn/src/deform_pool_cuda.cpp
nocv2easyocr/DBNet/assets/ops/dcn/src/deform_pool_cuda_kernel.cu
nocv2easyocr/DBNet/backbones/__init__.py
nocv2easyocr/DBNet/backbones/mobilenetv3.py
nocv2easyocr/DBNet/backbones/resnet.py
nocv2easyocr/DBNet/configs/DBNet_inference.yaml
nocv2easyocr/DBNet/decoders/__init__.py
nocv2easyocr/DBNet/decoders/balance_cross_entropy_loss.py
nocv2easyocr/DBNet/decoders/dice_loss.py
nocv2easyocr/DBNet/decoders/feature_attention.py
nocv2easyocr/DBNet/decoders/l1_loss.py
nocv2easyocr/DBNet/decoders/pss_loss.py
nocv2easyocr/DBNet/decoders/seg_detector.py
nocv2easyocr/DBNet/decoders/seg_detector_asf.py
nocv2easyocr/DBNet/decoders/seg_detector_loss.py
nocv2easyocr-0.1.1.dist-info/LICENSE
nocv2easyocr-0.1.1.dist-info/METADATA
nocv2easyocr-0.1.1.dist-info/WHEEL
nocv2easyocr-0.1.1.dist-info/entry_points.txt
nocv2easyocr-0.1.1.dist-info/top_level.txt
nocv2easyocr-0.1.1.dist-info/RECORD
