Metadata-Version: 2.1
Name: nocv2easyocr
Version: 0.1.1
Summary: This is a fork of the EasyOCR library without the opencv requirement
Home-page: https://github.com/jaidedai/easyocr
Download-URL: https://github.com/jaidedai/nocv2easyocr.git
Author: Rakpong Kittinaradorn
Author-email: r.kittinaradorn@gmail.com
License: Apache License 2.0
Keywords: ocr optical character recognition deep learning neural network
Classifier: Development Status :: 5 - Production/Stable
License-File: LICENSE
Requires-Dist: torch
Requires-Dist: torchvision (>=0.5)
Requires-Dist: scipy
Requires-Dist: numpy
Requires-Dist: Pillow
Requires-Dist: scikit-image
Requires-Dist: python-bidi
Requires-Dist: PyYAML
Requires-Dist: Shapely
Requires-Dist: pyclipper
Requires-Dist: ninja
